brand/__init__.py
brand/dev/__init__.py
brand/dev/_base_client.py
brand/dev/_client.py
brand/dev/_compat.py
brand/dev/_constants.py
brand/dev/_exceptions.py
brand/dev/_files.py
brand/dev/_models.py
brand/dev/_qs.py
brand/dev/_resource.py
brand/dev/_response.py
brand/dev/_streaming.py
brand/dev/_types.py
brand/dev/_version.py
brand/dev/py.typed
brand/dev/_utils/__init__.py
brand/dev/_utils/_compat.py
brand/dev/_utils/_datetime_parse.py
brand/dev/_utils/_logs.py
brand/dev/_utils/_proxy.py
brand/dev/_utils/_reflection.py
brand/dev/_utils/_resources_proxy.py
brand/dev/_utils/_streams.py
brand/dev/_utils/_sync.py
brand/dev/_utils/_transform.py
brand/dev/_utils/_typing.py
brand/dev/_utils/_utils.py
brand/dev/lib/.keep
brand/dev/resources/__init__.py
brand/dev/resources/brand.py
brand/dev/types/__init__.py
brand/dev/types/brand_ai_products_params.py
brand/dev/types/brand_ai_products_response.py
brand/dev/types/brand_ai_query_params.py
brand/dev/types/brand_ai_query_response.py
brand/dev/types/brand_fonts_params.py
brand/dev/types/brand_fonts_response.py
brand/dev/types/brand_identify_from_transaction_params.py
brand/dev/types/brand_identify_from_transaction_response.py
brand/dev/types/brand_prefetch_by_email_params.py
brand/dev/types/brand_prefetch_by_email_response.py
brand/dev/types/brand_prefetch_params.py
brand/dev/types/brand_prefetch_response.py
brand/dev/types/brand_retrieve_by_email_params.py
brand/dev/types/brand_retrieve_by_email_response.py
brand/dev/types/brand_retrieve_by_isin_params.py
brand/dev/types/brand_retrieve_by_isin_response.py
brand/dev/types/brand_retrieve_by_name_params.py
brand/dev/types/brand_retrieve_by_name_response.py
brand/dev/types/brand_retrieve_by_ticker_params.py
brand/dev/types/brand_retrieve_by_ticker_response.py
brand/dev/types/brand_retrieve_naics_params.py
brand/dev/types/brand_retrieve_naics_response.py
brand/dev/types/brand_retrieve_params.py
brand/dev/types/brand_retrieve_response.py
brand_dev-1.28.0.dist-info/METADATA
brand_dev-1.28.0.dist-info/WHEEL
brand_dev-1.28.0.dist-info/licenses/LICENSE
brand_dev-1.28.0.dist-info/RECORD
